pact_test/__init__.py
pact_test/clients/__init__.py
pact_test/clients/http_client.py
pact_test/config/__init__.py
pact_test/config/config_builder.py
pact_test/constants/__init__.py
pact_test/either/__init__.py
pact_test/matchers/__init__.py
pact_test/matchers/matcher.py
pact_test/matchers/request_matcher.py
pact_test/matchers/response_matcher.py
pact_test/models/__init__.py
pact_test/models/pact_helper.py
pact_test/models/request.py
pact_test/models/response.py
pact_test/models/service_consumer_test.py
pact_test/models/service_provider_test.py
pact_test/repositories/__init__.py
pact_test/repositories/pact_broker.py
pact_test/runners/__init__.py
pact_test/runners/pact_tests_runner.py
pact_test/runners/service_consumers/__init__.py
pact_test/runners/service_consumers/state_test.py
pact_test/runners/service_consumers/test_suite.py
pact_test/runners/service_providers/__init__.py
pact_test/runners/service_providers/request_test.py
pact_test/runners/service_providers/test_suite.py
pact_test/servers/__init__.py
pact_test/servers/mock_server.py
pact_test/utils/__init__.py
pact_test/utils/http_utils.py
pact_test/utils/logger.py
pact_test/utils/pact_helper_utils.py
pact_test/utils/pact_utils.py
pact_test-1.0.4.data/scripts/pact-test
tests/__init__.py
tests/acceptance/__init__.py
tests/acceptance/acceptance_test_loader.py
tests/resources/__init__.py
pact_test-1.0.4.dist-info/LICENSE
pact_test-1.0.4.dist-info/METADATA
pact_test-1.0.4.dist-info/WHEEL
pact_test-1.0.4.dist-info/top_level.txt
pact_test-1.0.4.dist-info/RECORD
