Metadata-Version: 2.1
Name: pact-test
Version: 1.0.4
Summary: Python implementation for Pact (http://pact.io/)
Home-page: https://github.com/Kalimaha/pact-test/
Author: Guido Barbaglia
Author-email: guido.barbaglia@gmail.com
License: LICENSE
Platform: UNKNOWN
Classifier: License :: OSI Approved :: MIT License
Classifier: Operating System :: OS Independent
Classifier: Programming Language :: Python :: 2.7
Classifier: Programming Language :: Python :: 3.3
Classifier: Programming Language :: Python :: 3.4
Classifier: Programming Language :: Python :: 3.5
Classifier: Programming Language :: Python :: 3.6
Classifier: Programming Language :: Python :: 3.7
Classifier: Programming Language :: Python :: 3.8
Classifier: Topic :: Software Development :: Testing
Requires-Dist: requests
